Week-1/Verilog ALU 4-BIT/ALU-4bit.v
module alu4bit(A, B, op_sel, ALU_output);
input [3:0] A, B;          
input [2:0] op_sel;       
output reg [3:0] ALU_output;
always @(*)
begin
	case(op_sel)
		3'b000: ALU_output = A + B;
		3'b001: ALU_output = A - B;
		3'b010: ALU_output = A * B;
		3'b011: ALU_output = A/B;
		3'b100: ALU_output = A & B;
		3'b101: ALU_output = A | B;
		3'b110: ALU_output = ~A;
		3'b111: ALU_output = ~B;
		default: ALU_output = A^B;
	endcase
end
endmodule

Week-1/Verilog ALU 4-BIT/ALU-4bit_tb.v
// Testbench

module alu4bit_TB();
reg [3:0] A, B;          
reg [2:0] op_sel;       
wire [3:0] ALU_output;

alu4bit instace_a1(A, B, op_sel, ALU_output);

initial
	begin
		$dumpfile("waveform.vcd");
		$dumpvars(0, alu4bit_TB);
		op_sel = 3'b000; A = 4'b1100; B = 4'b0011;
		#10;
		op_sel = 3'b001; A = 4'b1100; B = 4'b0011;
		#10;
		op_sel = 3'b010; A = 4'b1100; B = 4'b0011;
		#10;
		op_sel = 3'b011; A = 4'b1100; B = 4'b0011;
		#10;
		op_sel = 3'b100; A = 4'b1100; B = 4'b0011;
		#10;
		op_sel = 3'b101; A = 4'b1100; B = 4'b0011;
		#10;
		op_sel = 3'b110; A = 4'b1100; B = 4'b0011;
		#10;
		op_sel = 3'b111; A = 4'b1100; B = 4'b0011;
		#10;
	end
endmodule

Week-1/Verilog ALU 4-BIT/waveform.vcd
$date
	Fri May 24 19:08:15 2024
$end
$version
	Icarus Verilog
$end
$timescale
	1s
$end
$scope module alu4bit_TB $end
$var wire 4 ! ALU_output [3:0] $end
$var reg 4 " A [3:0] $end
$var reg 4 # B [3:0] $end
$var reg 3 $ op_sel [2:0] $end
$scope module instace_a1 $end
$var wire 4 % A [3:0] $end
$var wire 4 & B [3:0] $end
$var wire 3 ' op_sel [2:0] $end
$var reg 4 ( ALU_output [3:0] $end
$upscope $end
$upscope $end
$enddefinitions $end
#0
$dumpvars
b1111 (
b0 '
b11 &
b1100 %
b0 $
b11 #
b1100 "
b1111 !
$end
#10
b1001 !
b1001 (
b1 $
b1 '
#20
b100 !
b100 (
b10 $
b10 '
#30
b11 $
b11 '
#40
b0 !
b0 (
b100 $
b100 '
#50
b1111 !
b1111 (
b101 $
b101 '
#60
b11 !
b11 (
b110 $
b110 '
#70
b1100 !
b1100 (
b111 $
b111 '
